kiara_plugin/core_types/__init__.py
kiara_plugin/core_types/defaults.py
kiara_plugin/core_types/models.py
kiara_plugin/core_types/py.typed
kiara_plugin/core_types/version.txt
kiara_plugin/core_types/data_types/__init__.py
kiara_plugin/core_types/data_types/models.py
kiara_plugin/core_types/modules/__init__.py
kiara_plugin/core_types/modules/boolean.py
kiara_plugin/core_types/modules/date.py
kiara_plugin/core_types/modules/list.py
kiara_plugin/core_types/modules/models.py
kiara_plugin/core_types/modules/string.py
kiara_plugin/core_types/pipelines/.gitkeep
kiara_plugin/core_types/pipelines/__init__.py
kiara_plugin/core_types/pipelines/logic/nand.json
kiara_plugin/core_types/pipelines/logic/nor.json
kiara_plugin/core_types/pipelines/logic/xor.json
kiara_plugin/core_types/renderers/__init__.py
kiara_plugin/core_types/renderers/lineage.py
kiara_plugin/core_types/resources/.gitkeep
kiara_plugin_core_types-0.5.3.dist-info/METADATA
kiara_plugin_core_types-0.5.3.dist-info/WHEEL
kiara_plugin_core_types-0.5.3.dist-info/entry_points.txt
kiara_plugin_core_types-0.5.3.dist-info/licenses/AUTHORS.md
kiara_plugin_core_types-0.5.3.dist-info/licenses/LICENSE
kiara_plugin_core_types-0.5.3.dist-info/RECORD
