Metadata-Version: 2.4
Name: kiara_plugin.core_types
Version: 0.5.3
Summary: Core data types for kiara.
Project-URL: homepage, https://github.com/DHARPA-Project/kiara_plugin.core_types
Project-URL: documentation, https://DHARPA-Project.github.io/kiara_plugin.core_types
Project-URL: repository, https://github.com/DHARPA-Project/kiara_plugin.core_types
Author-email: Markus Binsteiner <markus@frkl.dev>
License: MPL-2.0
License-File: AUTHORS.md
License-File: LICENSE
Keywords: kiara,kiara-plugin
Classifier: Development Status :: 3 - Alpha
Classifier: License :: OSI Approved :: Mozilla Public License 2.0 (MPL 2.0)
Classifier: Programming Language :: Python
Classifier: Programming Language :: Python :: 3
Classifier: Programming Language :: Python :: 3 :: Only
Classifier: Programming Language :: Python :: 3.9
Classifier: Programming Language :: Python :: 3.10
Classifier: Programming Language :: Python :: 3.11
Classifier: Programming Language :: Python :: 3.12
Classifier: Programming Language :: Python :: 3.13
Requires-Python: >=3.9
Requires-Dist: kiara<0.6.0,>=0.5.13
Requires-Dist: python-dateutil>=2.8.0
Provides-Extra: jupyter
Requires-Dist: kiara[jupyter]; extra == 'jupyter'
Provides-Extra: marimo
Requires-Dist: kiara[marimo]; extra == 'marimo'
